MANIFEST.in
README.md
setup.py
pygattlib.egg-info/PKG-INFO
pygattlib.egg-info/SOURCES.txt
pygattlib.egg-info/dependency_links.txt
pygattlib.egg-info/top_level.txt
src/Makefile
src/att.o
src/beacon.cpp
src/beacon.h
src/beacon.o
src/bindings.cpp
src/bindings.o
src/btio.o
src/crypto.o
src/debug.h
src/event.hpp
src/gatt.o
src/gattlib.cpp
src/gattlib.h
src/gattlib.o
src/gattlib.so
src/gattrib.o
src/gattservices.cpp
src/gattservices.h
src/gattservices.o
src/log.o
src/utils.o
src/uuid.o
src/bluez/.git
src/bluez/.gitignore
src/bluez/.mailmap
src/bluez/AUTHORS
src/bluez/COPYING
src/bluez/COPYING.LIB
src/bluez/ChangeLog
src/bluez/HACKING
src/bluez/INSTALL
src/bluez/Makefile.am
src/bluez/Makefile.obexd
src/bluez/Makefile.plugins
src/bluez/Makefile.tools
src/bluez/NEWS
src/bluez/README
src/bluez/TODO
src/bluez/acinclude.m4
src/bluez/bootstrap
src/bluez/bootstrap-configure
src/bluez/configure.ac
src/bluez/android/Android.mk
src/bluez/android/Makefile.am
src/bluez/android/README
src/bluez/android/a2dp-sink.c
src/bluez/android/a2dp-sink.h
src/bluez/android/a2dp.c
src/bluez/android/a2dp.h
src/bluez/android/audio-ipc-api.txt
src/bluez/android/audio-msg.h
src/bluez/android/avctp.c
src/bluez/android/avctp.h
src/bluez/android/avdtp.c
src/bluez/android/avdtp.h
src/bluez/android/avdtptest.c
src/bluez/android/avrcp-lib.c
src/bluez/android/avrcp-lib.h
src/bluez/android/avrcp.c
src/bluez/android/avrcp.h
src/bluez/android/bluetooth.c
src/bluez/android/bluetooth.h
src/bluez/android/bluetoothd-snoop.c
src/bluez/android/bluetoothd-wrapper.c
src/bluez/android/bluetoothd.te
src/bluez/android/bluetoothd_snoop.te
src/bluez/android/cts.txt
src/bluez/android/gatt.c
src/bluez/android/gatt.h
src/bluez/android/hal-a2dp-sink.c
src/bluez/android/hal-a2dp.c
src/bluez/android/hal-audio-aptx.c
src/bluez/android/hal-audio-sbc.c
src/bluez/android/hal-audio.c
src/bluez/android/hal-audio.h
src/bluez/android/hal-avrcp-ctrl.c
src/bluez/android/hal-avrcp.c
src/bluez/android/hal-bluetooth.c
src/bluez/android/hal-gatt.c
src/bluez/android/hal-handsfree-client.c
src/bluez/android/hal-handsfree.c
src/bluez/android/hal-health.c
